pylsp_myplugin/__init__.py
pylsp_myplugin/plugin.py
test/__init__.py
test/conftest.py
test/test_plugin.py
pylsp_myplugin-0.1.dist-info/AUTHORS.txt
pylsp_myplugin-0.1.dist-info/LICENSE
pylsp_myplugin-0.1.dist-info/METADATA
pylsp_myplugin-0.1.dist-info/WHEEL
pylsp_myplugin-0.1.dist-info/entry_points.txt
pylsp_myplugin-0.1.dist-info/top_level.txt
pylsp_myplugin-0.1.dist-info/RECORD
