Metadata-Version: 2.1
Name: pylsp-myplugin
Version: 0.1
Summary: Package description for PyPI
Home-page: https://github.com/python-lsp/pylsp-myplugin
Author: Lie Ryan
Author-email: lie.1296@gmail.com
License: MIT license
Classifier: Programming Language :: Python
Classifier: Operating System :: OS Independent
Classifier: Development Status :: 2 - Pre-Alpha
Classifier: Intended Audience :: Developers
Classifier: Topic :: Text Editors :: Integrated Development Environments (IDE)
Classifier: Topic :: Software Development
Classifier: License :: OSI Approved :: MIT License
License-File: LICENSE
License-File: AUTHORS.txt
Requires-Dist: python-lsp-server
Provides-Extra: dev
Requires-Dist: pytest ; extra == 'dev'
Requires-Dist: build ; extra == 'dev'
Requires-Dist: twine ; extra == 'dev'
